codd.py
codd-0.2.2.dist-info/DESCRIPTION.rst
codd-0.2.2.dist-info/METADATA
codd-0.2.2.dist-info/RECORD
codd-0.2.2.dist-info/WHEEL
codd-0.2.2.dist-info/metadata.json
codd-0.2.2.dist-info/top_level.txt
