Metadata-Version: 2.0
Name: codd
Version: 0.2.2
Summary: relational alegrbra for functional programs
Home-page: http://github.com/trivio/codd
Author: Scott Robertson
Author-email: scott@triv.io
License: UNKNOWN
Platform: UNKNOWN
Classifier: Programming Language :: Python
Classifier: License :: OSI Approved :: MIT License
Classifier: Operating System :: OS Independent
Classifier: Development Status :: 3 - Alpha
Classifier: Intended Audience :: Developers
Classifier: Topic :: Software Development
Requires-Dist: xlocal
